log_analyzer_chenwenjun/__init__.py
log_analyzer_chenwenjun/analyzer.py
log_analyzer_chenwenjun/hello.py
log_analyzer_chenwenjun/innerRule.cp310-win_amd64.pyd
log_analyzer_chenwenjun/logAnalyzer.cp310-win_amd64.pyd
log_analyzer_chenwenjun-0.0.3.dist-info/METADATA
log_analyzer_chenwenjun-0.0.3.dist-info/WHEEL
log_analyzer_chenwenjun-0.0.3.dist-info/top_level.txt
log_analyzer_chenwenjun-0.0.3.dist-info/RECORD
