Metadata-Version: 2.1
Name: log-analyzer-chenwenjun
Version: 0.0.3
Summary: log analyze
Author: chenwenjun
Author-email: cwj129@126.com
License: apache 3.0
Requires: numpy
Requires: matplotlib
